pajek_tools/__init__.py
pajek_tools/cli.py
pajek_tools/config.py
pajek_tools/pajek_tools.py
pajek_tools-0.1.4.dist-info/AUTHORS.rst
pajek_tools-0.1.4.dist-info/LICENSE
pajek_tools-0.1.4.dist-info/METADATA
pajek_tools-0.1.4.dist-info/WHEEL
pajek_tools-0.1.4.dist-info/entry_points.txt
pajek_tools-0.1.4.dist-info/top_level.txt
pajek_tools-0.1.4.dist-info/RECORD
