Metadata-Version: 2.1
Name: pajek-tools
Version: 0.1.4
Summary: Tools for converting network data to pajek files
Home-page: https://github.com/h1-the-swan/pajek_tools
Author: Jason Portenoy
Author-email: jason.portenoy@gmail.com
License: MIT license
Keywords: pajek_tools
Platform: UNKNOWN
Classifier: Development Status :: 2 - Pre-Alpha
Classifier: Intended Audience :: Developers
Classifier: License :: OSI Approved :: MIT License
Classifier: Natural Language :: English
Classifier: Programming Language :: Python :: 3
Classifier: Programming Language :: Python :: 3.5
Classifier: Programming Language :: Python :: 3.6
Classifier: Programming Language :: Python :: 3.7
Classifier: Programming Language :: Python :: 3.8
Requires-Python: >=3.5
Requires-Dist: pandas
Requires-Dist: numpy
